[
  {
    "type_id": "BT-STD-PAL-01",
    "type_code": "STDPAL",
    "type_name": "Standard Pallet Bin",
    "description": "Standard size bin for pallet storage in main warehouse areas",
    "storage_class": "A",
    "standard_length": 120.0,
    "standard_width": 100.0,
    "standard_height": 200.0,
    "standard_volume": 2.4,
    "standard_weight": 15.0,
    "max_payload": 1000.0,
    "is_stackable": true,
    "max_stack_count": 3,
    "stackable_with": ["BT-STD-PAL-01", "BT-HVY-PAL-01"],
    "material": "high_density_plastic",
    "color": "blue",
    "is_transparent": false,
    "is_foldable": false,
    "requires_cleaning": false,
    "is_hazardous_material": false,
    "temperature_range": "-10 to +50 degrees Celsius",
    "default_barcode_prefix": "STDPAL",
    "default_color_code": "BLU",
    "label_position": "front_top",
    "average_cost": 85.00,
    "expected_lifespan_months": 60,
    "depreciation_rate": 20.0,
    "is_active": true,
    "custom_fields": {
      "manufacturer": "Schoeller Allibert",
      "model_number": "DOLAV-1200x1000",
      "certification": "UN_approved",
      "rfid_compatible": true
    },
    "notes": "Most commonly used bin type for general storage operations"
  },
  {
    "type_id": "BT-HVY-PAL-01",
    "type_code": "HVYPAL",
    "type_name": "Heavy Duty Pallet Bin",
    "description": "Reinforced bin for heavy items and industrial storage",
    "storage_class": "A",
    "standard_length": 120.0,
    "standard_width": 100.0,
    "standard_height": 200.0,
    "standard_volume": 2.4,
    "standard_weight": 22.0,
    "max_payload": 2000.0,
    "is_stackable": true,
    "max_stack_count": 2,
    "stackable_with": ["BT-HVY-PAL-01", "BT-STD-PAL-01"],
    "material": "reinforced_plastic",
    "color": "red",
    "is_transparent": false,
    "is_foldable": false,
    "requires_cleaning": false,
    "is_hazardous_material": false,
    "temperature_range": "-20 to +60 degrees Celsius",
    "default_barcode_prefix": "HVYPAL",
    "default_color_code": "RED",
    "label_position": "front_top",
    "average_cost": 145.00,
    "expected_lifespan_months": 84,
    "depreciation_rate": 15.0,
    "is_active": true,
    "custom_fields": {
      "manufacturer": "SSI Schaefer",
      "model_number": "RLC-1208-HD",
      "load_rating": "2000kg",
      "forklift_compatible": true
    },
    "notes": "Used for heavy industrial parts and equipment storage"
  },
  {
    "type_id": "BT-LGT-PAL-01",
    "type_code": "LGTPAL",
    "type_name": "Light Duty Pallet Bin",
    "description": "Lightweight bin for smaller items and top-level storage",
    "storage_class": "B",
    "standard_length": 120.0,
    "standard_width": 100.0,
    "standard_height": 150.0,
    "standard_volume": 1.8,
    "standard_weight": 10.0,
    "max_payload": 500.0,
    "is_stackable": true,
    "max_stack_count": 5,
    "stackable_with": ["BT-LGT-PAL-01"],
    "material": "lightweight_plastic",
    "color": "green",
    "is_transparent": false,
    "is_foldable": true,
    "requires_cleaning": false,
    "is_hazardous_material": false,
    "temperature_range": "0 to +40 degrees Celsius",
    "default_barcode_prefix": "LGTPAL",
    "default_color_code": "GRN",
    "label_position": "front_center",
    "average_cost": 55.00,
    "expected_lifespan_months": 48,
    "depreciation_rate": 25.0,
    "is_active": true,
    "custom_fields": {
      "manufacturer": "Plastibac",
      "model_number": "PB-1200-LW",
      "weight_capacity": "500kg",
      "nest_when_empty": true
    },
    "notes": "Ideal for light products and upper level storage locations"
  },
  {
    "type_id": "BT-PCK-BIN-01",
    "type_code": "PCKBIN",
    "type_name": "Standard Pick Bin",
    "description": "Small bin for order picking operations and fast-moving items",
    "storage_class": "C",
    "standard_length": 40.0,
    "standard_width": 30.0,
    "standard_height": 20.0,
    "standard_volume": 0.024,
    "standard_weight": 0.8,
    "max_payload": 25.0,
    "is_stackable": true,
    "max_stack_count": 8,
    "stackable_with": ["BT-PCK-BIN-01", "BT-PCK-BIN-02"],
    "material": "polypropylene",
    "color": "yellow",
    "is_transparent": true,
    "is_foldable": false,
    "requires_cleaning": true,
    "cleaning_frequency_days": 30,
    "is_hazardous_material": false,
    "temperature_range": "-5 to +40 degrees Celsius",
    "default_barcode_prefix": "PICK",
    "default_color_code": "YEL",
    "label_position": "front_lip",
    "average_cost": 12.50,
    "expected_lifespan_months": 36,
    "depreciation_rate": 30.0,
    "is_active": true,
    "custom_fields": {
      "manufacturer": "Akro-Mils",
      "model_number": "AKR-30240",
      "divider_compatible": true,
      "hang_bin_compatible": false
    },
    "notes": "Primary bin for fast-moving SKUs in picking areas"
  },
  {
    "type_id": "BT-PCK-BIN-02",
    "type_code": "PCKBINS",
    "type_name": "Small Pick Bin",
    "description": "Extra small bin for very small items and high-density picking",
    "storage_class": "C",
    "standard_length": 30.0,
    "standard_width": 20.0,
    "standard_height": 15.0,
    "standard_volume": 0.009,
    "standard_weight": 0.4,
    "max_payload": 10.0,
    "is_stackable": true,
    "max_stack_count": 12,
    "stackable_with": ["BT-PCK-BIN-01", "BT-PCK-BIN-02"],
    "material": "polypropylene",
    "color": "clear",
    "is_transparent": true,
    "is_foldable": false,
    "requires_cleaning": true,
    "cleaning_frequency_days": 30,
    "is_hazardous_material": false,
    "temperature_range": "-5 to +40 degrees Celsius",
    "default_barcode_prefix": "PICKS",
    "default_color_code": "CLR",
    "label_position": "front_lip",
    "average_cost": 8.75,
    "expected_lifespan_months": 24,
    "depreciation_rate": 35.0,
    "is_active": true,
    "custom_fields": {
      "manufacturer": "Akro-Mils",
      "model_number": "AKR-30230S",
      "divider_compatible": true,
      "optimal_for": "small_parts"
    },
    "notes": "Used for small electronic components and accessories"
  },
  {
    "type_id": "BT-COLD-BIN-01",
    "type_code": "COLDBIN",
    "type_name": "Cold Storage Bin",
    "description": "Insulated bin designed for cold storage and refrigerated areas",
    "storage_class": "A",
    "standard_length": 80.0,
    "standard_width": 60.0,
    "standard_height": 40.0,
    "standard_volume": 0.192,
    "standard_weight": 3.5,
    "max_payload": 50.0,
    "is_stackable": true,
    "max_stack_count": 4,
    "stackable_with": ["BT-COLD-BIN-01"],
    "material": "insulated_plastic",
    "color": "white",
    "is_transparent": false,
    "is_foldable": false,
    "requires_cleaning": true,
    "cleaning_frequency_days": 7,
    "is_hazardous_material": false,
    "temperature_range": "-25 to +8 degrees Celsius",
    "default_barcode_prefix": "COLD",
    "default_color_code": "WHT",
    "label_position": "top_center",
    "average_cost": 95.00,
    "expected_lifespan_months": 60,
    "depreciation_rate": 20.0,
    "is_active": true,
    "custom_fields": {
      "manufacturer": "Cambro",
      "model_number": "ColdFlex-CF80",
      "insulation_rating": "R-8",
      "food_grade": true,
      "temperature_monitoring": "compatible"
    },
    "notes": "Specifically designed for perishable goods and cold chain logistics"
  },
  {
    "type_id": "BT-HAZ-BIN-01",
    "type_code": "HAZBIN",
    "type_name": "Hazardous Material Bin",
    "description": "Specialized bin for storing hazardous materials with safety features",
    "storage_class": "A",
    "standard_length": 100.0,
    "standard_width": 80.0,
    "standard_height": 60.0,
    "standard_volume": 0.48,
    "standard_weight": 8.0,
    "max_payload": 100.0,
    "is_stackable": false,
    "max_stack_count": 1,
    "stackable_with": [],
    "material": "chemical_resistant_plastic",
    "color": "orange",
    "is_transparent": false,
    "is_foldable": false,
    "requires_cleaning": true,
    "cleaning_frequency_days": 1,
    "is_hazardous_material": true,
    "temperature_range": "-10 to +35 degrees Celsius",
    "default_barcode_prefix": "HAZ",
    "default_color_code": "ORG",
    "label_position": "all_sides",
    "average_cost": 280.00,
    "expected_lifespan_months": 48,
    "depreciation_rate": 25.0,
    "is_active": true,
    "custom_fields": {
      "manufacturer": "Eagle Manufacturing",
      "model_number": "HAZ-1608",
      "un_certification": "UN4G/Y145/S",
      "spill_containment": true,
      "ventilation_required": true,
      "safety_rating": "Class_A"
    },
    "notes": "Must be used for all Class A hazardous materials. Special handling procedures required."
  },
  {
    "type_id": "BT-RET-BIN-01",
    "type_code": "RETBIN",
    "type_name": "Returns Processing Bin",
    "description": "Bin specifically for returned merchandise and refurbishment operations",
    "storage_class": "B",
    "standard_length": 60.0,
    "standard_width": 40.0,
    "standard_height": 30.0,
    "standard_volume": 0.072,
    "standard_weight": 1.8,
    "max_payload": 30.0,
    "is_stackable": true,
    "max_stack_count": 6,
    "stackable_with": ["BT-RET-BIN-01"],
    "material": "recycled_plastic",
    "color": "grey",
    "is_transparent": false,
    "is_foldable": false,
    "requires_cleaning": true,
    "cleaning_frequency_days": 14,
    "is_hazardous_material": false,
    "temperature_range": "5 to +35 degrees Celsius",
    "default_barcode_prefix": "RET",
    "default_color_code": "GRY",
    "label_position": "front_top",
    "average_cost": 42.00,
    "expected_lifespan_months": 42,
    "depreciation_rate": 28.0,
    "is_active": true,
    "custom_fields": {
      "manufacturer": "EcoPlastics",
      "model_number": "ECO-RET-6040",
      "eco_friendly": true,
      "inspection_window": true,
      "quality_control": "compatible"
    },
    "notes": "Used in returns processing area for quality inspection and refurbishment"
  },
  {
    "type_id": "BT-BLK-BIN-01",
    "type_code": "BLKBIN",
    "type_name": "Bulk Storage Bin",
    "description": "Large capacity bin for bulk storage of loose materials",
    "storage_class": "A",
    "standard_length": 150.0,
    "standard_width": 120.0,
    "standard_height": 180.0,
    "standard_volume": 3.24,
    "standard_weight": 28.0,
    "max_payload": 1500.0,
    "is_stackable": true,
    "max_stack_count": 2,
    "stackable_with": ["BT-BLK-BIN-01"],
    "material": "high_impact_plastic",
    "color": "black",
    "is_transparent": false,
    "is_foldable": true,
    "requires_cleaning": false,
    "is_hazardous_material": false,
    "temperature_range": "-15 to +50 degrees Celsius",
    "default_barcode_prefix": "BULK",
    "default_color_code": "BLK",
    "label_position": "front_top",
    "average_cost": 195.00,
    "expected_lifespan_months": 72,
    "depreciation_rate": 18.0,
    "is_active": true,
    "custom_fields": {
      "manufacturer": "GeoBin",
      "model_number": "GB-1500-HD",
      "forklift_compatible": true,
      "drain_plug": true,
      "reinforced_corners": true
    },
    "notes": "Ideal for raw materials and bulk commodity storage"
  },
  {
    "type_id": "BT-TOTE-01",
    "type_code": "TOTE",
    "type_name": "Standard Tote Bin",
    "description": "Multi-purpose tote bin for order consolidation and transport",
    "storage_class": "C",
    "standard_length": 60.0,
    "standard_width": 40.0,
    "standard_height": 22.0,
    "standard_volume": 0.053,
    "standard_weight": 1.2,
    "max_payload": 35.0,
    "is_stackable": true,
    "max_stack_count": 10,
    "stackable_with": ["BT-TOTE-01", "BT-TOTE-02"],
    "material": "copolymer_plastic",
    "color": "blue",
    "is_transparent": false,
    "is_foldable": false,
    "requires_cleaning": true,
    "cleaning_frequency_days": 30,
    "is_hazardous_material": false,
    "temperature_range": "-10 to +45 degrees Celsius",
    "default_barcode_prefix": "TOTE",
    "default_color_code": "BLU",
    "label_position": "short_end",
    "average_cost": 28.50,
    "expected_lifespan_months": 48,
    "depreciation_rate": 25.0,
    "is_active": true,
    "custom_fields": {
      "manufacturer": "Rubbermaid Commercial",
      "model_number": "RCP-TOTE-2400",
      "nesting_capability": true,
      "ergonomic_handles": true,
      "conveyor_compatible": true
    },
    "notes": "Primary container for order picking and inter-warehouse transfers"
  },
  {
    "type_id": "BT-TOTE-02",
    "type_code": "TOTESM",
    "type_name": "Small Tote Bin",
    "description": "Compact tote bin for small orders and parts picking",
    "storage_class": "C",
    "standard_length": 42.0,
    "standard_width": 30.0,
    "standard_height": 18.0,
    "standard_volume": 0.023,
    "standard_weight": 0.8,
    "max_payload": 20.0,
    "is_stackable": true,
    "max_stack_count": 15,
    "stackable_with": ["BT-TOTE-01", "BT-TOTE-02"],
    "material": "copolymer_plastic",
    "color": "red",
    "is_transparent": false,
    "is_foldable": false,
    "requires_cleaning": true,
    "cleaning_frequency_days": 30,
    "is_hazardous_material": false,
    "temperature_range": "-10 to +45 degrees Celsius",
    "default_barcode_prefix": "TOTESM",
    "default_color_code": "RED",
    "label_position": "short_end",
    "average_cost": 18.75,
    "expected_lifespan_months": 36,
    "depreciation_rate": 30.0,
    "is_active": true,
    "custom_fields": {
      "manufacturer": "Rubbermaid Commercial",
      "model_number": "RCP-TOTE-1800",
      "nesting_capability": true,
      "single_handed_carry": true,
      "space_efficient": true
    },
    "notes": "Perfect for e-commerce fulfillment and small part assembly operations"
  }
]